autozoom/__init__.py
autozoom/__main__.py
autozoom-0.1.23.dist-info/METADATA
autozoom-0.1.23.dist-info/WHEEL
autozoom-0.1.23.dist-info/top_level.txt
autozoom-0.1.23.dist-info/RECORD
