Metadata-Version: 2.1
Name: autozoom
Version: 0.1.23
Summary: Based on a schedule enter zoom meetings
Home-page: https://github.com/DogAteMyCode/autozoom
Author: VoidNull
Author-email: nullvoid0div0@protonmail.com
License: MIT
Platform: UNKNOWN
Classifier: Programming Language :: Python :: 3
Classifier: License :: OSI Approved :: MIT License
Classifier: Operating System :: MacOS
Requires-Python: >=3.6
Requires-Dist: pyperclip
Requires-Dist: keyboard (>0.13.0)
Requires-Dist: requests
Requires-Dist: texttable
